{
  "clientData": [
    {
      "id": 1,
      "name": "Mi Cuenta Citibanamex",
      "balance": 1000,
      "client": "Victoria Tejeda",
      "typeAccount": true,
      "maximumAmount": 3000.00,
      "displayAccountNumber": "9078653487565656",
      "email": "example@mail.com",
    },
    {
      "id": 2,
      "name": "Cuenta Priority Citibanamex - 8799",
      "balance": 200,
      "client": "Victoria Tejeda",
      "typeAccount": true,
      "maximumAmount": 3000.00,
      "displayAccountNumber": "9078676451264638",
      "email": "example@mail.com",
    },
    {
      "id": 3,
      "name": "Business Checking",
      "client": "Melissa Leyva",
      "typeAccount": false,
      "maximumAmount": 3000.00,
      "displayAccountNumber": "9432253738503219",
      "email": "exampleotro@mail.com",
    }
  ]
}